MANIFEST.in
setup.py
Configure/DataBaseInfo.ini
Configure/DataBaseName.json
Configure/all-luban-subsystem-db-config.ini
Configure/commTable.ini
Configure/whiteList.ini
Configure/wordsrelatetodb.ini
DatabaseCommander/ConnectDB.py
DatabaseCommander/DataBaseUserInfo.py
DatabaseCommander/OperateDataBase.py
DatabaseCommander/__init__.py
DatabaseCommander/mongooperate.py
PublicMethod/OperateIniFile.py
PublicMethod/OperationJson.py
PublicMethod/ReadDataBaseUserInfo.py
PublicMethod/ReadIniFile.py
PublicMethod/__init__.py
ZipCommander/__init__.py
ZipCommander/zipfiledata.py
comparedbdata.egg-info/PKG-INFO
comparedbdata.egg-info/SOURCES.txt
comparedbdata.egg-info/dependency_links.txt
comparedbdata.egg-info/requires.txt
comparedbdata.egg-info/top_level.txt
testcase/__init__.py
testcase/run_export_out.py
testcase/test_common_data.py
testcase/test_eqid_correlation_data.py
testcase/test_white_config_data.py