Metadata-Version: 1.0
Name: comparedbdata
Version: 1.0.3
Summary: 数据对比程序
Home-page: UNKNOWN
Author: jack_chen
Author-email: 375285942@qq.com
License: UNKNOWN
Platform: all
